subword_nmt/__init__.py
subword_nmt/apply_bpe.py
subword_nmt/bpe_toy.py
subword_nmt/chrF.py
subword_nmt/command_line.py
subword_nmt/get_vocab.py
subword_nmt/learn_bpe.py
subword_nmt/learn_joint_bpe_and_vocab.py
subword_nmt/segment-char-ngrams.py
subword_nmt/segment_char_ngrams.py
subword_nmt/subword_nmt.py
subword_nmt/tests/__init__.py
subword_nmt/tests/test_bpe.py
subword_nmt/tests/test_glossaries.py
subword_nmt-0.3.7.dist-info/METADATA
subword_nmt-0.3.7.dist-info/RECORD
subword_nmt-0.3.7.dist-info/WHEEL
subword_nmt-0.3.7.dist-info/entry_points.txt
subword_nmt-0.3.7.dist-info/top_level.txt
