Metadata-Version: 2.1
Name: subword-nmt
Version: 0.3.7
Summary: Unsupervised Word Segmentation for Neural Machine Translation and Text Generation
Home-page: https://github.com/rsennrich/subword-nmt
Author: Rico Sennrich
License: MIT
Platform: UNKNOWN
Classifier: Intended Audience :: Developers
Classifier: Topic :: Text Processing
Classifier: Topic :: Scientific/Engineering :: Artificial Intelligence
Classifier: License :: OSI Approved :: MIT License
Classifier: Programming Language :: Python :: 2
Classifier: Programming Language :: Python :: 3
